raiden_common/__init__.py
raiden_common/__main__.py
raiden_common/_monkey.py
raiden_common/accounts.py
raiden_common/constants.py
raiden_common/exceptions.py
raiden_common/log_config.py
raiden_common/message_handler.py
raiden_common/py.typed
raiden_common/raiden_event_handler.py
raiden_common/raiden_service.py
raiden_common/routing.py
raiden_common/services.py
raiden_common/settings.py
raiden_common/tasks.py
raiden_common/waiting.py
raiden_common/api/__init__.py
raiden_common/api/exceptions.py
raiden_common/api/objects.py
raiden_common/api/python.py
raiden_common/api/rest.py
raiden_common/api/rest_utils.py
raiden_common/api/v1/__init__.py
raiden_common/api/v1/encoding.py
raiden_common/api/v1/resources.py
raiden_common/blockchain/__init__.py
raiden_common/blockchain/decode.py
raiden_common/blockchain/events.py
raiden_common/blockchain/exceptions.py
raiden_common/blockchain/filters.py
raiden_common/blockchain/middleware.py
raiden_common/blockchain/state.py
raiden_common/blockchain/utils.py
raiden_common/messages/__init__.py
raiden_common/messages/abstract.py
raiden_common/messages/cmdid.py
raiden_common/messages/decode.py
raiden_common/messages/encode.py
raiden_common/messages/healthcheck.py
raiden_common/messages/metadata.py
raiden_common/messages/monitoring_service.py
raiden_common/messages/path_finding_service.py
raiden_common/messages/synchronization.py
raiden_common/messages/transfers.py
raiden_common/messages/withdraw.py
raiden_common/network/__init__.py
raiden_common/network/pathfinding.py
raiden_common/network/utils.py
raiden_common/network/proxies/__init__.py
raiden_common/network/proxies/custom_token.py
raiden_common/network/proxies/exceptions.py
raiden_common/network/proxies/metadata.py
raiden_common/network/proxies/monitoring_service.py
raiden_common/network/proxies/one_to_n.py
raiden_common/network/proxies/payment_channel.py
raiden_common/network/proxies/proxy_manager.py
raiden_common/network/proxies/secret_registry.py
raiden_common-0.1.8.dist-info/LICENSE
raiden_common-0.1.8.dist-info/METADATA
raiden_common-0.1.8.dist-info/WHEEL
raiden_common-0.1.8.dist-info/top_level.txt
raiden_common-0.1.8.dist-info/RECORD
