Metadata-Version: 2.1
Name: raiden-common
Version: 0.1.8
Summary: Common code between python-based Raiden projects 
Home-page: https://github.com/raiden-network/raiden-common
Author: Brainbot Labs Est.
Author-email: contact@brainbot.li
License: MIT
Keywords: raiden
Classifier: Development Status :: 4 - Beta
Classifier: Intended Audience :: Developers
Classifier: License :: OSI Approved :: MIT License
Classifier: Natural Language :: English
Classifier: Programming Language :: Python :: 3
Classifier: Programming Language :: Python :: 3.8
Classifier: Programming Language :: Python :: 3.9
Requires-Python: >=3.8
License-File: LICENSE
Requires-Dist: aiohttp (==3.7.4.post0)
Requires-Dist: aniso8601 (==7.0.0)
Requires-Dist: asn1crypto (==1.3.0)
Requires-Dist: async-timeout (==3.0.1)
Requires-Dist: attrs (==19.3.0)
Requires-Dist: base58 (==2.0.0)
Requires-Dist: bitarray (==2.6.0)
Requires-Dist: cachetools (==4.2.4)
Requires-Dist: canonicaljson (==1.6.3)
Requires-Dist: certifi (==2019.3.9)
Requires-Dist: cffi (==1.15.1)
Requires-Dist: chardet (==3.0.4)
Requires-Dist: charset-normalizer (==2.0.2)
Requires-Dist: click (==8.1.3)
Requires-Dist: coincurve (==15.0.1)
Requires-Dist: colorama (==0.4.4)
Requires-Dist: cytoolz (==0.12.0)
Requires-Dist: dbapi-opentracing (==0.0.5)
Requires-Dist: eciespy (==0.3.12)
Requires-Dist: eth-abi (==3.0.1)
Requires-Dist: eth-account (==0.7.0)
Requires-Dist: eth-hash[pycryptodome] (==0.3.3)
Requires-Dist: eth-keyfile (==0.6.0)
Requires-Dist: eth-keys (==0.4.0)
Requires-Dist: eth-rlp (==0.3.0)
Requires-Dist: eth-typing (==3.2.0)
Requires-Dist: eth-utils (==2.0.0)
Requires-Dist: filelock (==3.6.0)
Requires-Dist: flask (==2.1.3)
Requires-Dist: flask-cors (==3.0.10)
Requires-Dist: flask-opentracing (==1.1.0)
Requires-Dist: flask-restful (==0.3.9)
Requires-Dist: gevent (==21.12.0)
Requires-Dist: graphviz (==0.13.2)
Requires-Dist: greenlet (==1.1.2)
Requires-Dist: guppy3 (==3.1.2)
Requires-Dist: hexbytes (==0.3.0)
Requires-Dist: idna (==2.8)
Requires-Dist: importlib-metadata (==5.0.0)
Requires-Dist: ipfshttpclient (==0.8.0a2)
Requires-Dist: itsdangerous (==2.0.1)
Requires-Dist: jinja2 (==3.0.3)
Requires-Dist: jsonschema (==4.16.0)
Requires-Dist: lru-dict (==1.1.6)
Requires-Dist: markupsafe (==2.0.1)
Requires-Dist: marshmallow (==3.18.0)
Requires-Dist: marshmallow-dataclass[union] (==8.5.9)
Requires-Dist: marshmallow-enum (==1.5.1)
Requires-Dist: marshmallow-polyfield (==5.10)
Requires-Dist: matrix-client (==0.3.2)
Requires-Dist: multiaddr (==0.0.9)
Requires-Dist: multidict (==5.1.0)
Requires-Dist: mypy-extensions (==0.4.3)
Requires-Dist: netaddr (==0.7.19)
Requires-Dist: objgraph (==3.5.0)
Requires-Dist: opentracing (==2.3.0)
Requires-Dist: packaging (==21.3)
Requires-Dist: parsimonious (==0.8.1)
Requires-Dist: protobuf (==3.20.1)
Requires-Dist: psutil (==5.8.0)
Requires-Dist: py-solc-x (==1.1.0)
Requires-Dist: pycparser (==2.19)
Requires-Dist: pycryptodome (==3.15.0)
Requires-Dist: pyparsing (==2.4.7)
Requires-Dist: pyrsistent (==0.15.7)
Requires-Dist: pysha3 (==1.0.2)
Requires-Dist: pytz (==2019.1)
Requires-Dist: raiden-contracts (==0.50.2)
Requires-Dist: raiden-webui (==1.2.1)
Requires-Dist: requests (==2.28.1)
Requires-Dist: requests-opentracing (==0.3.0)
Requires-Dist: rlp (==3.0.0)
Requires-Dist: semantic-version (==2.8.5)
Requires-Dist: simplejson (==3.17.2)
Requires-Dist: six (==1.16.0)
Requires-Dist: structlog (==21.5.0)
Requires-Dist: toml (==0.10.2)
Requires-Dist: toolz (==0.12.0)
Requires-Dist: typeguard (==2.11.1)
Requires-Dist: typing-extensions (==4.4.0)
Requires-Dist: typing-inspect (==0.8.0)
Requires-Dist: ulid-py (==1.1.0)
Requires-Dist: urllib3 (==1.26.5)
Requires-Dist: varint (==1.0.2)
Requires-Dist: web3 (==6.0.0b6)
Requires-Dist: websockets (==10.3)
Requires-Dist: werkzeug (==2.0.1)
Requires-Dist: wrapt (==1.12.1)
Requires-Dist: yarl (==1.6.3)
Requires-Dist: zipp (==3.8.1)
Requires-Dist: zope-event (==4.4)
Requires-Dist: zope-interface (==5.1.0)
